hcp_vault_secrets/__init__.py
hcp_vault_secrets/vaultsecrets.py
hcp_vault_secrets/lib/__init__.py
hcp_vault_secrets/lib/logging.py
hcp_vault_secrets-0.0.5.dist-info/METADATA
hcp_vault_secrets-0.0.5.dist-info/WHEEL
hcp_vault_secrets-0.0.5.dist-info/RECORD
